onnxslim/__init__.py
onnxslim/__main__.py
onnxslim/argparser.py
onnxslim/utils.py
onnxslim/version.py
onnxslim/cli/__init__.py
onnxslim/cli/_main.py
onnxslim/core/__init__.py
onnxslim/core/optimization/__init__.py
onnxslim/core/optimization/dead_node_elimination.py
onnxslim/core/optimization/subexpression_elimination.py
onnxslim/core/optimization/weight_tying.py
onnxslim/core/pattern/__init__.py
onnxslim/core/pattern/registry.py
onnxslim/core/pattern/elimination/__init__.py
onnxslim/core/pattern/elimination/concat.py
onnxslim/core/pattern/elimination/reshape.py
onnxslim/core/pattern/elimination/reshape_as.py
onnxslim/core/pattern/elimination/slice.py
onnxslim/core/pattern/elimination/unsqueeze.py
onnxslim/core/pattern/fusion/__init__.py
onnxslim/core/pattern/fusion/concat_reshape.py
onnxslim/core/pattern/fusion/convadd.py
onnxslim/core/pattern/fusion/convbn.py
onnxslim/core/pattern/fusion/convmul.py
onnxslim/core/pattern/fusion/gelu.py
onnxslim/core/pattern/fusion/gemm.py
onnxslim/core/pattern/fusion/padconv.py
onnxslim/core/pattern/fusion/reduce.py
onnxslim/misc/__init__.py
onnxslim/misc/tabulate.py
onnxslim/third_party/__init__.py
onnxslim/third_party/symbolic_shape_infer.py
onnxslim/third_party/_sympy/__init__.py
onnxslim/third_party/_sympy/functions.py
onnxslim/third_party/_sympy/numbers.py
onnxslim/third_party/_sympy/printers.py
onnxslim/third_party/_sympy/solve.py
onnxslim/third_party/_sympy/symbol.py
onnxslim/third_party/onnx_graphsurgeon/__init__.py
onnxslim/third_party/onnx_graphsurgeon/exporters/__init__.py
onnxslim/third_party/onnx_graphsurgeon/exporters/base_exporter.py
onnxslim/third_party/onnx_graphsurgeon/exporters/onnx_exporter.py
onnxslim/third_party/onnx_graphsurgeon/graph_pattern/__init__.py
onnxslim/third_party/onnx_graphsurgeon/graph_pattern/graph_pattern.py
onnxslim/third_party/onnx_graphsurgeon/importers/__init__.py
onnxslim/third_party/onnx_graphsurgeon/importers/base_importer.py
onnxslim-0.1.80.dist-info/licenses/LICENSE
onnxslim-0.1.80.dist-info/METADATA
onnxslim-0.1.80.dist-info/WHEEL
onnxslim-0.1.80.dist-info/entry_points.txt
onnxslim-0.1.80.dist-info/top_level.txt
onnxslim-0.1.80.dist-info/zip-safe
onnxslim-0.1.80.dist-info/RECORD
