Metadata-Version: 2.4
Name: onnxslim
Version: 0.1.80
Summary: OnnxSlim: A Toolkit to Help Optimize Onnx Model
Home-page: https://github.com/inisis/OnnxSlim
Author: inisis
Author-email: desmond.yao@buaa.edu.cn
License: MIT
Project-URL: Bug Tracker, https://github.com/inisis/OnnxSlim/issues
Classifier: Programming Language :: Python :: 3
Classifier: License :: OSI Approved :: MIT License
Classifier: Intended Audience :: Developers
Classifier: Topic :: Scientific/Engineering :: Artificial Intelligence
Requires-Python: >=3.6
License-File: LICENSE
Requires-Dist: onnx
Requires-Dist: sympy>=1.13.1
Requires-Dist: packaging
Requires-Dist: colorama
Requires-Dist: ml_dtypes
Dynamic: author
Dynamic: author-email
Dynamic: classifier
Dynamic: description
Dynamic: description-content-type
Dynamic: home-page
Dynamic: license
Dynamic: license-file
Dynamic: project-url
Dynamic: requires-dist
Dynamic: requires-python
Dynamic: summary
